{"num":157,"name":"root","children":[{"num":53,"name":"6_0_0","children":[{"num":14,"name":"6_1_0","children":[{"num":4,"name":"6_1_0","children":[{"num":1,"name":"Lewis's medical-surgical nursing : assessment and management of clinical problems / edited by Diane"},{"num":1,"name":"The gold standard GAMSAT / editor and author, Brett Ferdinand ; contributors, Lisa Ferdinand, Sean P"},{"num":1,"name":"Contexts of nursing : an introduction / edited by John Daly, Sandra Speedy, Debra Jackson."},{"num":1,"name":"Transitions in nursing : preparing for professional practice / edited by Professor Esther Chang, Pro"}],"categoryName":"Medical sciences; Medicine"},{"num":1,"name":"6_1_1","children":[{"num":1,"name":"Histology : a text and atlas : with correlated cell and molecular biology / Michael H. Ross, Wojciec"}],"categoryName":"Human anatomy, cytology, histology"},{"num":2,"name":"6_1_5","children":[{"num":1,"name":"Therapeutic kinesiology : musculoskeletal systems, palpation, and body mechanics / Mary Ann Foster."},{"num":1,"name":"The complete guide to exercise therapy / Christopher M. Norris."}],"categoryName":"Pharmacology and therapeutics"},{"num":6,"name":"6_1_6","children":[{"num":5,"name":"Rubin's pathology : clinicopathologic foundations of medicine."},{"num":1,"name":"Experimenting with humans and animals : from Galen to animal rights / Anita Guerrini."}],"categoryName":"Diseases"},{"num":1,"name":"6_1_2","children":[{"num":1,"name":"The Cold War & the university : toward an intellectual history of the postwar years / Noam Chomsky ."}],"categoryName":"Human physiology"}],"categoryName":"Medical sciences; Medicine"},{"num":37,"name":"6_5_0","children":[{"num":31,"name":"6_5_8","children":[{"num":1,"name":"Human resource management : strategy and practice / Alan Nankervis, Marian Baird, Jane Coffey, John"},{"num":2,"name":"Fundamentals of corporate finance / Stephen Ross, Michael Drew, Adam Walk, Randolph Westerfield, Bra"},{"num":2,"name":"ACCT2 managerial / Prabhu Sivabalan, Roby Sawyers, Steve Jackson, Greg Jenkins."},{"num":4,"name":"Management control systems : performance measurement, evaluation and incentives / Kenneth A. Merchan"},{"num":1,"name":"Financial management : principles and applications / J. William Petty ... [et al.]."},{"num":1,"name":"Essentials of corporate finance / Stephen A. Ross ... [et al.]."},{"num":1,"name":"Fundamentals of corporate finance / Stephen Ross, Robert Bianchi, Mark Christensen, Michael Drew, Ra"},{"num":3,"name":"Value proposition design : how to create products and services customers want / Alexander Osterwalde"},{"num":1,"name":"Managing & organizations : an introduction to theory and practice / Stewart R Clegg, Martin Kornberg"},{"num":1,"name":"International business strategy : theory and practice / edited by Peter J Buckley and Pervez N Ghaur"},{"num":1,"name":"Business strategy and sustainability / ed. by Guler Aras and David Crowther."},{"num":1,"name":"Business strategy : managing uncertainty, opportunity, and enterprise / J.-C. Spender."},{"num":1,"name":"Business and sustainability / Michael Blowfield."},{"num":1,"name":"Exploring strategy / Gerry Johnson, Richard Whittington, Kevan Scholes, Duncan Angwin, Patrick Regne"},{"num":2,"name":"Business model generation : a handbook for visionaries, game changers, and challengers / written by"},{"num":1,"name":"Organizational change, leadership and ethics : leading organizations toward sustainability / edited"},{"num":1,"name":"An introduction to Prince2 : managing and directing successful projects."},{"num":1,"name":"Successful project management / Trevor L. Young."},{"num":2,"name":"Management accounting : information for creating and managing value / Kim Langfield-Smith ; Helen Th"},{"num":1,"name":"Blue ocean strategy : how to create uncontested market space and make the competition irrelevant / W"},{"num":1,"name":"Supply chain management and advanced planning : concepts, models, software and case studies / Hartmu"},{"num":1,"name":"Sustainability in Australian business : fundamental principles and practice / Geoffrey Wells."}],"categoryName":"General management"},{"num":4,"name":"6_5_7","children":[{"num":3,"name":"Business process integration with SAP ERP / Berhard Wieder."},{"num":1,"name":"Corporate accounting : a custom publication / prepared by Peter Lam, Anna Loyeung, Yaowen Shan"}],"categoryName":"Accounting"},{"num":2,"name":"6_5_9","children":[{"num":2,"name":"Becoming a public relations writer : a strategic writing workbook for emerging and established media"}],"categoryName":"Advertising & public relations"}],"categoryName":"Management & auxiliary services"},{"num":2,"name":"6_2_0","children":[{"num":1,"name":"6_2_1","children":[{"num":1,"name":"Electrical power transmission system engineering : analysis and design / Turan Gonen."}],"categoryName":"Applied physics"},{"num":1,"name":"6_2_4","children":[{"num":1,"name":"A dictionary of construction, surveying, and civil engineering / by Christopher Gorse, David Johnsto"}],"categoryName":"Civil engineering"}],"categoryName":"Engineering & Applied operations"}],"categoryName":"Technology"},{"num":65,"name":"3_0_0","children":[{"num":5,"name":"3_6_0","children":[{"num":1,"name":"3_6_3","children":[{"num":1,"name":"Polar oceans governance in an era of environmental change / edited by Tim Stephens, Faculty of law,"}],"categoryName":"Other social problems & services"},{"num":4,"name":"3_6_2","children":[{"num":1,"name":"Suicidal behaviours in men : determinants and prevention in Australia / Kairi Kolves ; Eeva-Katri Ku"},{"num":1,"name":"Aboriginal suicide is different : a portrait of life and self-destruction / Colin Tatz."},{"num":2,"name":"LIFE : living is for everyone : a framework for prevention of suicide and self-harm in Australia."}],"categoryName":"Social welfare problems & services"}],"categoryName":"Social services; association"},{"num":1,"name":"3_5_0","children":[{"num":1,"name":"3_5_3","children":[{"num":1,"name":"The fiscal crisis of the state / [by] James O'Connor"}],"categoryName":"Of U.S. federal & state governments"}],"categoryName":"Public administration"},{"num":4,"name":"3_7_0","children":[{"num":1,"name":"3_7_4","children":[{"num":1,"name":"Musing budding musos : the role of peer mentoring in learning to be a contemporary musician / Ross S"}],"categoryName":"Adult education"},{"num":1,"name":"3_7_8","children":[{"num":1,"name":"Reverse mentoring : critical journeys ; what my students taught me / edited by Dr. Jim Towns."}],"categoryName":"Higher education"},{"num":1,"name":"3_7_0","children":[{"num":1,"name":"Peer-group mentoring for teacher development / edited by Hannu L.T. Heikkinen, Hannu Jokinen & Paivi"}],"categoryName":"Education"},{"num":1,"name":"3_7_2","children":[{"num":1,"name":"Maths is all around you : developing mathematical concepts in the early years / Marianne Knaus."}],"categoryName":"Elementary education"}],"categoryName":"Education"},{"num":14,"name":"3_3_0","children":[{"num":2,"name":"3_3_0","children":[{"num":1,"name":"Economics for today / Allan Layton, Tim Robinson, Irvin B. Tucker."},{"num":1,"name":"Economics for management (custom edition) / compiled by Harry Tse."}],"categoryName":"Economics"},{"num":2,"name":"3_3_8","children":[{"num":1,"name":"Oligopoly pricing : old ideas and new tools / Xavier Vives."},{"num":1,"name":"Business forecasting / John E. Hanke, Dean Wichern."}],"categoryName":"Production"},{"num":4,"name":"3_3_1","children":[{"num":4,"name":"The economics of imperfect labor markets / Tito Boeri and Jan van Ours."}],"categoryName":"Labor economics"},{"num":6,"name":"3_3_2","children":[{"num":4,"name":"Financial institutions, instruments and markets / Christopher Viney, Peter Phillips."},{"num":1,"name":"The hungry dragon : how China's resource quest is reshaping the world / Sigfrido Burgos Caceres, Sop"},{"num":1,"name":"Property development / Sara Wilkinson and Richard Reed."}],"categoryName":"Financial economics"}],"categoryName":"Economics"},{"num":32,"name":"3_4_0","children":[{"num":25,"name":"3_4_7","children":[{"num":1,"name":"Corporations law / Colin Anderson, Jennifer Dickfos, Margaret Hyland, Marina Nehme, Andrew Dahdal."},{"num":1,"name":"Corporations law / Colin Anderson ; Jennifer Dickfos ; Margaret Hyland ; Andrew M Dahdal."},{"num":2,"name":"Meagher, Gummow and Lehane's equity : doctrines and remedies / R. P. Meagher, J. D. Heydon, M. J. Le"},{"num":1,"name":"Principles of Australian equity and trusts / Peter Radan, Cameron Stewart."},{"num":1,"name":"Intellectual property in Australia / Andrew Stewart, Philip Griffith, Judith Bannister."},{"num":1,"name":"Copyfight / edited by Phillipa McGuinness."},{"num":2,"name":"Keay's Insolvency : personal and corporate law and practice / Murray, Michael, Jason Harris."},{"num":1,"name":"Technology licensing : a practitioner's guide / Heather Meeker."},{"num":2,"name":"Company law : theories, principles and applications / Jason Harris."},{"num":1,"name":"Social media and the law / Patrick George (General Editor), Monica Allen, Stefanie Benson, Michael B"},{"num":1,"name":"Cyberspace law : commentaries and materials / Yee Fen Lim."},{"num":1,"name":"Civil procedure in New South Wales / Miiko Kumar ; Michael Legg ; Ilija Vickovich."},{"num":1,"name":"Equity and trusts / Michael Evans, Bradley L Jones."},{"num":1,"name":"Mediation : practice, policy, and ethics / Carrie J. Menkel-Meadow, Chancellor's Professor of Law an"},{"num":1,"name":"Fugitive identity of mediation : negotiations, shift changes and allusionary action / Debbie De Giro"},{"num":1,"name":"Alternative dispute resolution / Tania Sourdin."},{"num":1,"name":"Dispute resolution in Australia : cases, commentary and materials / David Spencer, Dr Samantha Hardy"},{"num":2,"name":"The Australian consumer law / S G Corones."},{"num":2,"name":"Civil remedies / M.J. Tilbury."},{"num":1,"name":"Principles of contemporary corporate governance / Jean Jacques du Plessis, Anil Hargovan, Mirko Baga"}],"categoryName":"Civil procedure & courts"},{"num":2,"name":"3_4_5","children":[{"num":2,"name":"Statutory interpretation in Australia / Emeritus Professor Dennis C Pearce AO ; Adjunct Professor Ro"}],"categoryName":"Criminal law"},{"num":2,"name":"3_4_1","children":[{"num":1,"name":"International law : cases and materials with Australian perspectives / Donald R. Rothwell, Stuart Ka"},{"num":1,"name":"International environmental treaty making / edited by Lawrence E. Susskind, Eric Jay Dolin and J. Wi"}],"categoryName":"International law"},{"num":3,"name":"3_4_6","children":[{"num":1,"name":"The courts and the media : challenges in the era of digital and social media / edited by Patrick Key"},{"num":1,"name":"Principles of Australian constitutional law / Patrick Keyzer, Christopher Goff, Asaf Fisher."},{"num":1,"name":"Control of government action : text, cases and commentary / Robin Creyke, John McMillan, Mark Smyth."}],"categoryName":"Private law"}],"categoryName":"Law"},{"num":6,"name":"3_0_0","children":[{"num":1,"name":"3_0_3","children":[{"num":1,"name":"Agitation with a smile : Howard Zinn's legacies and the future of activism / edited by Stephen Bird,"}],"categoryName":"Social processes"},{"num":5,"name":"3_0_2","children":[{"num":1,"name":"A contrastive analysis of English and Vietnamese / by Nguy en ang Liem"},{"num":1,"name":"The consensus building handbook : a comprehensive guide to reaching agreement / editors, Lawrence Su"},{"num":1,"name":"Convergent media and privacy / Tim Dwyer, University of Sydney, Australia."},{"num":1,"name":"Sharing our lives online : risks and exposure in social media / David R. Brake."},{"num":1,"name":"Bodily communication / Michael Argyle"}],"categoryName":"Social interaction"}],"categoryName":"Social sciences"},{"num":3,"name":"3_2_0","children":[{"num":3,"name":"3_2_7","children":[{"num":3,"name":"International law / Malcolm Shaw."}],"categoryName":"International relations"}],"categoryName":"Political science"}],"categoryName":"Social sciences"},{"num":4,"name":"0_0_0","children":[{"num":3,"name":"0_0_0","children":[{"num":1,"name":"0_0_6","children":[{"num":1,"name":"Data mining : concepts and techniques / Jiawei Han, Micheline Kamber, Jian Pei."}],"categoryName":"Special computer methods"},{"num":2,"name":"0_0_5","children":[{"num":1,"name":"Modern database management / Jeffrey A. Hoffer, University of Dayton, V. Ramesh, Indiana University,"},{"num":1,"name":"Modern database management / Jeffrey A. Hoffer, V. Ramesh, Heikki Topi."}],"categoryName":"Computer programming, programs & data"}],"categoryName":"Computer science, knowledge & systems"},{"num":1,"name":"0_6_0","children":[{"num":1,"name":"0_6_9","children":[{"num":1,"name":"Engaging heritage, engaging communities / edited by Bryony Onciul, Michelle L. Stefano and Stephanie"}],"categoryName":"Museum science"}],"categoryName":"Associations, organizations & museums"}],"categoryName":"Computer science, information & general works"},{"num":9,"name":"5_0_0","children":[{"num":1,"name":"5_3_0","children":[{"num":1,"name":"5_3_7","children":[{"num":1,"name":"Electric circuits / James W. Nilsson, Professor Emeritus, Iowa State University, Susan A. Riedel, Ma"}],"categoryName":"Electricity & electronics"}],"categoryName":"Physics"},{"num":6,"name":"5_1_0","children":[{"num":6,"name":"5_1_9","children":[{"num":6,"name":"Probability and statistics for engineering and the sciences / Jay Devore."}],"categoryName":"Probabilities & applied mathematics"}],"categoryName":"Mathematics"},{"num":1,"name":"5_7_0","children":[{"num":1,"name":"5_7_9","children":[{"num":1,"name":"Anatomy & physiology : an integrative approach / Michael P. McKinley, Glendale Community College, Va"}],"categoryName":"Microorganisms, fungi, algae"}],"categoryName":"Life sciences"},{"num":1,"name":"5_9_0","children":[{"num":1,"name":"5_9_1","children":[{"num":1,"name":"Last animals at the zoo : how mass extinction can be stopped / Colin Tudge"}],"categoryName":"Zoology"}],"categoryName":"Zoological sciences/Animals"}],"categoryName":"Science"},{"num":3,"name":"8_0_0","children":[{"num":2,"name":"8_2_0","children":[{"num":1,"name":"8_2_3","children":[{"num":1,"name":"Festival & special event management / Johnny Allen ... [et al.]."}],"categoryName":"English fiction"},{"num":1,"name":"8_2_2","children":[{"num":1,"name":"Romeo and Juliet / written by William Shakespeare ; retold by Martin Powell ; illustrated by Eva Cab"}],"categoryName":"English drama"}],"categoryName":"English & Old English literatures"},{"num":1,"name":"8_0_0","children":[{"num":1,"name":"8_0_8","children":[{"num":1,"name":"Dracula /  Bram Stoker ; illustrated by Penko Gelev ; retold by Fiona Macdonald"}],"categoryName":"Rhetoric & collections of literature"}],"categoryName":"Literature, rhetoric & criticism"}],"categoryName":"Literature"},{"num":20,"name":"7_0_0","children":[{"num":12,"name":"7_2_0","children":[{"num":12,"name":"7_2_0","children":[{"num":4,"name":"World architecture : a cross-cultural history / Richard Ingersoll, Spiro Kostof."},{"num":1,"name":"Thinking architecture / Peter Zumthor"},{"num":1,"name":"New directions in Australian architecture / Philip Goad, editor: Patrick Bingham-Hall"},{"num":1,"name":"Ecological living : what architecture for a more sustainable city? / [translated by Jonathan Sly]."},{"num":1,"name":"150 best eco house ideas / [editor and text, Marta Serrats]."},{"num":1,"name":"Ecominimalism : the antidote to eco-bling / Howard Liddell."},{"num":1,"name":"Strategies for sustainable architecture / Paola Sassi."},{"num":1,"name":"Towards zero energy architecture : new solar design / Mary Guzowski."},{"num":1,"name":"The architecture of Tokyo : an architectural history in 571 individual presentations / by Hiroshi Wa"}],"categoryName":"Architecture"}],"categoryName":"Architecture"},{"num":4,"name":"7_9_0","children":[{"num":2,"name":"7_9_1","children":[{"num":1,"name":"Akira [videorecording] / character design, script and direction by Katsuhiro Otomo ; English adaptat"},{"num":1,"name":"Loaded / Christos Tsiolkas."}],"categoryName":"Public performances"},{"num":2,"name":"7_9_6","children":[{"num":1,"name":"The ugly game : the corruption of FIFA and the Qatari plot to buy the World Cup / Heidi Blake and Jo"},{"num":1,"name":"Ethics and morality in sport management / Joy T. Desensi, Danny Rosenberg."}],"categoryName":"Athletic & outdoor sports & games"}],"categoryName":"Recreational & performing arts"},{"num":1,"name":"7_3_0","children":[{"num":1,"name":"7_3_8","children":[{"num":1,"name":"Potter & Perry's fundamentals of nursing / Australian adaptation edited by Jackie Crisp, Clint Dougl"}],"categoryName":"Ceramic arts"}],"categoryName":"Plastic arts; Sculpture"},{"num":1,"name":"7_1_0","children":[{"num":1,"name":"7_1_1","children":[{"num":1,"name":"Urban structuring : studies of Alison & Peter Smithson"}],"categoryName":"Area planning (Civic art)"}],"categoryName":"Civic & landscape art"},{"num":2,"name":"7_4_0","children":[{"num":2,"name":"7_4_1","children":[{"num":1,"name":"Sleeping Beauty the graphic novel / retold by Martin Powell ; illustrated by Sean Dietrich."},{"num":1,"name":"Raven's gate : the graphic novel / Anthony Horowitz ; adapted by Tony Lee ; illustrated by Dom Reard"}],"categoryName":"Drawing & drawings"}],"categoryName":"Drawing & decorative arts"}],"categoryName":"Arts & recreation"},{"num":2,"name":"1_0_0","children":[{"num":1,"name":"1_7_0","children":[{"num":1,"name":"1_7_0","children":[{"num":1,"name":"Ethics & law for Australian nurses / Kim Atkins, Bonnie Britton, Sheryl de Lacey."}],"categoryName":"Ethics"}],"categoryName":"Ethics (Moral philosophy)"},{"num":1,"name":"1_5_0","children":[{"num":1,"name":"1_5_8","children":[{"num":1,"name":"The language of negotiation : a handbook of practical strategies for improving communication / Joan"}],"categoryName":"Applied psychology"}],"categoryName":"Psychology"}],"categoryName":"Philosophy and psychology"},{"num":1,"name":"4_0_0","children":[{"num":1,"name":"4_2_0","children":[{"num":1,"name":"4_2_8","children":[{"num":1,"name":"Etpedia : 1,000 ideas for english language teachers."}],"categoryName":"Standard English usage"}],"categoryName":"English & Old English"}],"categoryName":"Language"}],"categoryName":"root"}