{"num": 239, "name": "root", "children": [{"num": 73, "name": "3", "children": [{"num": 21, "name": "33", "children": [{"num": 8, "name": "338", "children": [{"num": 7, "name": "Business forecasting / John E. Hanke, Dean W. Wichern."}, {"num": 1, "name": "Chocolate nations : living and dying for cocoa in West Africa / Orla Ryan."}]}, {"num": 5, "name": "330", "children": [{"num": 2, "name": "Economics for managers / Paul G. Farnham, Georgia State University."}, {"num": 1, "name": "Econometrics by example / Damodar Gujarati"}, {"num": 1, "name": "Basic econometrics / Damodar N. Gujarati, Dawn C. Porter."}, {"num": 1, "name": "Principles of economics / Joshua Gans, Stephen King, Robin Stonecash, N. Gregory Mankiw."}]}, {"num": 6, "name": "332", "children": [{"num": 1, "name": "Principles of investments / Anup Basu ; Michael E. Drew ; Zvi Bodie ; Alex Kane ; Alan J. Marcus."}, {"num": 1, "name": "Financial institutions and markets / Ben Hunt ; Chris Terry."}, {"num": 2, "name": "Financial institutions and markets / Chris Terry, Ben Hunt."}, {"num": 1, "name": "Financial institutions and markets / Ben Hunt & Chris Terry."}, {"num": 1, "name": "Benjamin Graham, building a profession : classic writings of the father of security analysis / Jason"}]}, {"num": 2, "name": "331", "children": [{"num": 1, "name": "Employment relations : theory and practice / Mark Bray, Peter Waring, Rae Cooper, Johanna MacNeil."}, {"num": 1, "name": "Worker identity, agency and economic development : women's empowerment in the Indian informal econom"}]}]}, {"num": 28, "name": "34", "children": [{"num": 16, "name": "347", "children": [{"num": 1, "name": "Equity in commercial law / edited by Simone Degeling, James Edelman."}, {"num": 2, "name": "The law of defamation and the Internet / Matthew Collins."}, {"num": 2, "name": "Banking law in Australia / Alan L. Tyree."}, {"num": 1, "name": "The legal nature of unit trust / Kam Fan Sin."}, {"num": 3, "name": "Meagher, Gummow and Lehane's equity : doctrines and remedies / R. P. Meagher, J. D. Heydon, M. J. Le"}, {"num": 1, "name": "Principles of Australian equity and trusts / Peter Radan, Cameron Stewart."}, {"num": 1, "name": "Equity and trusts / Peter Radan, Cameron Stewart, Andrew Lynch."}, {"num": 1, "name": "NSW civil procedure handbook / general editor, John P Hamilton ... [et al.]."}, {"num": 1, "name": "Australian civil procedure / B.C. Cairns."}, {"num": 2, "name": "Understanding company law / Phillip Lipton, Abe Herzberg."}, {"num": 1, "name": "The new lawyer : how settlement is transforming the practice of law / Julie Macfarlane."}]}, {"num": 10, "name": "341", "children": [{"num": 1, "name": "International humanitarian law / Emily Crawford and Alison Pert."}, {"num": 1, "name": "As a woman : writing women's lives / edited by Jocelynne A. Scutt"}, {"num": 1, "name": "Oceans governance in the twenty-first century : managing the blue planet / Marcus Haward, Joanna Vin"}, {"num": 1, "name": "The legal order of the oceans : basic documents on the law of the sea / edited by A.V. Lowe and S.A."}, {"num": 1, "name": "Dispute resolution in the law of the sea / by Igor V. Karaman."}, {"num": 1, "name": "Submissions to the UN CLCS in cases of disputed and undisputed maritime boundary delimitations or ot"}, {"num": 1, "name": "The guilt of nations : restitution and negotiating historical injustices / Elazar Barkan."}, {"num": 1, "name": "International trade law : commentary and materials / by Michael Pryles, Jeff Waincymer, Martin Davie"}, {"num": 1, "name": "Mergers & acquisitions : an insider's guide to the purchase and sale of middle market business inter"}, {"num": 1, "name": "International law : contemporary principles and practices / Gillian D Triggs."}]}, {"num": 2, "name": "340", "children": [{"num": 2, "name": "The law quarterly review"}]}]}, {"num": 2, "name": "38", "children": [{"num": 2, "name": "388", "children": [{"num": 1, "name": "Mr. Beck's underground map / Ken Garland."}, {"num": 1, "name": "Pyrmont & Ultimo history / Michael R. Matthews"}]}]}, {"num": 3, "name": "32", "children": [{"num": 1, "name": "323", "children": [{"num": 1, "name": "Neoliberalism as exception : mutations in citizenship and sovereignty / Aihwa Ong."}]}, {"num": 1, "name": "327", "children": [{"num": 1, "name": "International law / Malcolm Shaw."}]}, {"num": 1, "name": "320", "children": [{"num": 1, "name": "Machiavelli : a biography / Miles J. Unger."}]}]}, {"num": 13, "name": "30", "children": [{"num": 1, "name": "301", "children": [{"num": 1, "name": "The discovery of grounded theory : strategies for qualitative research / [by] Barney G. Glaser and A"}]}, {"num": 1, "name": "304", "children": [{"num": 1, "name": "Topophilia : A study of environmental perception, attitudes and values / Yi-Fu Tuan"}]}, {"num": 2, "name": "307", "children": [{"num": 1, "name": "Modeling cities and regions as complex systems : from theory to planning applications / Roger White,"}, {"num": 1, "name": "Evaluation for participation and sustainability in planning / edited by Angela Hull ... [et al.]."}]}, {"num": 2, "name": "306", "children": [{"num": 1, "name": "City worlds / edited by Doreen Massey, John Allen & Steve Pile."}, {"num": 1, "name": "Understanding the social economy and the third sector / Simon Bridge, Brendan Murtagh, and Ken O'Nei"}]}, {"num": 2, "name": "305", "children": [{"num": 1, "name": "Disciplining the savages : savaging the disciplines / Martin Nakata."}, {"num": 1, "name": "Ways of seeing / a book made by John Berger ... [et al]"}]}, {"num": 4, "name": "303", "children": [{"num": 1, "name": "The rise of the creative class : and how it's transforming work, leisure, community and everyday lif"}, {"num": 1, "name": "Understanding leadership perspectives : theoretical and practical approaches / Matthew R. Fairholm,"}, {"num": 1, "name": "Contemporary issues in leadership / edited by William E. Rosenbach, Robert L. Taylor, and Mark A. Yo"}, {"num": 1, "name": "Leadership studies : the dialogue of disciplines / edited by Michael Harvey, Ronald E. Riggio."}]}, {"num": 1, "name": "302", "children": [{"num": 1, "name": "Speech, music, sound / Theo van Leeuwen."}]}]}, {"num": 2, "name": "36", "children": [{"num": 2, "name": "362", "children": [{"num": 1, "name": "Transformational leadership in nursing / [edited by] Ann Marriner-Tomey"}, {"num": 1, "name": "Women and poverty in 21st century America / Paula vW. Dail."}]}]}, {"num": 4, "name": "37", "children": [{"num": 2, "name": "374", "children": [{"num": 1, "name": "Certificate III in spoken and written English / [NSW Adult Migrant English Service] ; [contributing"}, {"num": 1, "name": "Assessment guidelines for the Certificate in spoken and written English / Catherine Burrows"}]}, {"num": 2, "name": "370", "children": [{"num": 2, "name": "Doing your research project : a guide for first-time researchers in education, health and social sci"}]}]}]}, {"num": 13, "name": "4", "children": [{"num": 1, "name": "41", "children": [{"num": 1, "name": "411", "children": [{"num": 1, "name": "Handbook of the International Phonetic Association : a guide to the use of the International Phoneti"}]}]}, {"num": 8, "name": "42", "children": [{"num": 8, "name": "428", "children": [{"num": 1, "name": "Sound foundations : learning and teaching pronunciation / Adrian Underhill."}, {"num": 1, "name": "English grammar for students of German : the study guide for those learning German / Cecile Zorach,"}, {"num": 1, "name": "Word watching : field notes from an amateur philologist / Julian Burnside."}, {"num": 1, "name": "Cambridge English for job-hunting / Colm Downes."}, {"num": 1, "name": "Cambridge English for engineering / Mark Ibbotson."}, {"num": 1, "name": "Global. Intermediate."}, {"num": 1, "name": "Professional English in use. engineering : technical English for professionals / Mark Ibbotson."}, {"num": 1, "name": "English for social purposes : a handbook for teachers of adult literacy / Jenny Hammond ... [et al.]"}]}]}, {"num": 2, "name": "40", "children": [{"num": 2, "name": "401", "children": [{"num": 2, "name": "Working with discourse : meaning beyond the clause / J.R. Martin and David Rose."}]}]}, {"num": 2, "name": "46", "children": [{"num": 2, "name": "468", "children": [{"num": 1, "name": "Mexican Spanish."}, {"num": 1, "name": "The ultimate Spanish review and practice / Ronnie L. Gordon, David M. Stillman."}]}]}]}, {"num": 112, "name": "6", "children": [{"num": 34, "name": "61", "children": [{"num": 4, "name": "616", "children": [{"num": 1, "name": "Human parasitology / Burton J. Bogitsh, Clint E. Carter, Thomas N. Oeltmann."}, {"num": 1, "name": "Virtually you : the dangerous powers of the e-personality / Elias Aboujaoude."}, {"num": 1, "name": "Fluid physiology and pathology in traditional Chinese medicine / Steven Clavey."}, {"num": 1, "name": "Textbook of diagnostic microbiology / [edited by] Connie R. Mahon, Donald C. Lehman, George Manuseli"}]}, {"num": 20, "name": "610", "children": [{"num": 6, "name": "Lewis's medical-surgical nursing : assessment and management of clinical problems / Diane Brown ; He"}, {"num": 8, "name": "Lewis's medical-surgical nursing : assessment and management of clinical problems / edited by Diane"}, {"num": 2, "name": "Clinical psychomotor skills : assessment tools for nurses / Joanne Tollefson, Elspeth Hillman."}, {"num": 1, "name": "Transformational nursing leadership : a vision for the future / Anne M. Barker"}, {"num": 1, "name": "Medical-surgical nursing."}, {"num": 2, "name": "The foundations of Chinese medicine : a comprehensive text / Giovanni Maciocia, C.Ac. (Nanjing), acu"}]}, {"num": 1, "name": "614", "children": [{"num": 1, "name": "Australia's climate change policy : our economy, our environment, our future"}]}, {"num": 2, "name": "618", "children": [{"num": 1, "name": "Midwifery : preparation for practice / Sally Pairman ... [et al.]."}, {"num": 1, "name": "The midwife-mother relationship / edited by Mavis Kirkham."}]}, {"num": 6, "name": "615", "children": [{"num": 3, "name": "Flesh and bones of medical pharmacology / Domenico Spina ; illustrations by Robin Dean."}, {"num": 1, "name": "The celestial stems / by Royston Low"}, {"num": 1, "name": "Tuina therapy : treatment of adults and children / Weizhong Sun; Arne Kapner."}, {"num": 1, "name": "Traditional Chinese medicine cupping therapy / Ilkay Z. Chirali ; foreword by Michael McIntyre"}]}, {"num": 1, "name": "613", "children": [{"num": 1, "name": "Health, illness and wellbeing : perspectives and social determinants / edited by Pranee Liamputtong,"}]}]}, {"num": 6, "name": "69", "children": [{"num": 5, "name": "696", "children": [{"num": 5, "name": "Sustainable house / Michael Mobbs."}]}, {"num": 1, "name": "690", "children": [{"num": 1, "name": "Rawlinson's Australian construction handbook."}]}]}, {"num": 2, "name": "63", "children": [{"num": 2, "name": "635", "children": [{"num": 2, "name": "Sustainable food / Michael Mobbs."}]}]}, {"num": 66, "name": "65", "children": [{"num": 57, "name": "658", "children": [{"num": 1, "name": "Communication audits / Cal W. Downs"}, {"num": 5, "name": "Assessing organizational communication : strategic communication audits / Cal W. Downs, Allyson D. A"}, {"num": 1, "name": "Marketing / Greg Elliott ; Sharyn Rundle-Thiele ; David Waller."}, {"num": 4, "name": "Business computing : using Microsoft Office 2013 / Greg Pazmandy, David Bedford & Jakob Govendir."}, {"num": 1, "name": "Management accounting : information for creating and managing value / Kim Langfield-Smith, Helen Tho"}, {"num": 3, "name": "Luxury brand management : a world of privilege / Michel Chevalier, Gerald Mazzalovo."}, {"num": 1, "name": "Marketing : the retro revolution / Stephen Brown."}, {"num": 2, "name": "Management control systems : performance measurement, evaluation and incentives / Kenneth A. Merchan"}, {"num": 1, "name": "International financial management / Jeff Madura."}, {"num": 1, "name": "Giving effective feedback : foster positive change, influence behavior, strengthen relationships."}, {"num": 3, "name": "Operations and supply chain management."}, {"num": 1, "name": "How to get started with English language learners [videorecording] / produced by the Association for"}, {"num": 1, "name": "International project management / by Kathrin Koster."}, {"num": 2, "name": "Coaching and mentoring supervision : theory and practice / edited by Tatiana Bachkirova, Peter Jacks"}, {"num": 2, "name": "Coaching and mentoring : theory and practice / Bob Garvey, Paul Stokes and David Megginson."}, {"num": 2, "name": "Facilitating reflective learning : coaching, mentoring and supervison / Anne Brockbank, Ian McGill."}, {"num": 2, "name": "The elements of mentoring / W. Brad Johnson and Charles R. Ridley."}, {"num": 2, "name": "Everyone needs a mentor / David Clutterbuck"}, {"num": 2, "name": "Performance management / Herman Aguinis."}, {"num": 1, "name": "Human resource management in Australia : strategy, people, performance / Robin Kramar, Timothy Bartr"}, {"num": 1, "name": "Marketing scales handbook : a compilation of multi-item measures / Gordon C. Bruner II, Paul J. Hens"}, {"num": 2, "name": "CB / Barry J. Babin, Eric G. Harris."}, {"num": 2, "name": "Consumer behaviour : implications for marketing strategy / Cathy Neal ... [et al.]."}, {"num": 2, "name": "Service operations management : strategy, design, and delivery / Christine Hope and Alan Muhlemann."}, {"num": 2, "name": "Duct tape selling : think like a marketer, sell like a superstar / John Jantsch."}, {"num": 2, "name": "Marketing : an introduction / Gary Armstrong, Philip Kotler."}, {"num": 2, "name": "An empirical investigation of the performance of a situational multi-attribute model in predicting c"}, {"num": 2, "name": "Packaging in the marketing mix / Peter Danton de Rouffignac"}, {"num": 1, "name": "Marketing research : an integrated approach / Alan Wilson."}, {"num": 1, "name": "Business computing : using Microsoft Office / Greg Pazmandy."}, {"num": 1, "name": "Art of M&A valuation and modeling : a guide to corporate valuation / Peter Nesvold, Elizabeth Bloome"}, {"num": 1, "name": "Qualitative research in business : a practical overview / by Alf H. Walle."}]}, {"num": 5, "name": "657", "children": [{"num": 1, "name": "Accounting information systems : understanding business processes / Brett Considine ... [et al.]."}, {"num": 2, "name": "MYOB AccountRightPlus : a practical guide to computer accounting / by Greg Pazmandy."}, {"num": 1, "name": "Corporate accounting : a custom publication / prepared by Peter Lam, Anna Loyeung, Yaowen Shan"}, {"num": 1, "name": "MYOB version 17 : a practical guide to computer accounting / by Greg Pazmandy."}]}, {"num": 4, "name": "659", "children": [{"num": 3, "name": "Strategic planning for public relations / Ronald D. Smith."}, {"num": 1, "name": "Excellence in public relations and communication management / edited by James E. Grunig with David M"}]}]}, {"num": 4, "name": "62", "children": [{"num": 2, "name": "624", "children": [{"num": 1, "name": "Principles of geotechnical engineering / Braja M. Das."}, {"num": 1, "name": "Engineering principles of ground modification / Manfred R. Hausmann"}]}, {"num": 1, "name": "628", "children": [{"num": 1, "name": "Fire debris analysis / Julia Ann Dolan, Reta Newman, ERic Stauffer."}]}, {"num": 1, "name": "620", "children": [{"num": 1, "name": "Prestressed concrete / Warner, Faulkes, Foster."}]}]}]}, {"num": 7, "name": "5", "children": [{"num": 1, "name": "59", "children": [{"num": 1, "name": "590", "children": [{"num": 1, "name": "Integrated principles of zoology / Cleveland P. Hickman, Jr., Larry S. Roberts, Allan Larson ; origi"}]}]}, {"num": 2, "name": "51", "children": [{"num": 1, "name": "519", "children": [{"num": 1, "name": "Games of strategy / Avinash Dixit, Susan Skeath, David Reiley."}]}, {"num": 1, "name": "510", "children": [{"num": 1, "name": "New signpost mathematics 8 : stage 4 / Alan McSeveny, Rob Conway, Steve Wilkes."}]}]}, {"num": 2, "name": "55", "children": [{"num": 2, "name": "550", "children": [{"num": 2, "name": "Remote sensing of the environment : an earth resource perspective / John R. Jensen."}]}]}, {"num": 2, "name": "57", "children": [{"num": 2, "name": "577", "children": [{"num": 2, "name": "Australian freshwater ecology : processes and management / Andrew Boulton, Margaret Brock."}]}]}]}, {"num": 22, "name": "7", "children": [{"num": 7, "name": "72", "children": [{"num": 3, "name": "720", "children": [{"num": 1, "name": "Design games for architecture : creating digital design tools with Unity / Aaron Westre."}, {"num": 1, "name": "Introduction to architectural science : the basis of sustainable design / Steven K. Szokolay ; graph"}, {"num": 1, "name": "Motivating change : sustainable design and behaviour in the built environment / edited by Robert Cro"}]}, {"num": 2, "name": "728", "children": [{"num": 1, "name": "Rethinking historical distance / edited by Mark Salber Phillips (Professor of History, Carleton Univ"}, {"num": 1, "name": "Eames House : Charles and Ray Eames / James Steele."}]}, {"num": 2, "name": "729", "children": [{"num": 1, "name": "The colour, light and contrast manual : designing and managing inclusive built environments / Keith"}, {"num": 1, "name": "Rough interiors / Sibylle Kramer."}]}]}, {"num": 1, "name": "70", "children": [{"num": 1, "name": "705", "children": [{"num": 1, "name": "Art museum libraries and librarianship / edited by Joan M. Benedetti."}]}]}, {"num": 8, "name": "74", "children": [{"num": 5, "name": "746", "children": [{"num": 1, "name": "Obsessive creative / Collette Dinnigan."}, {"num": 1, "name": "New fashion designers' sketchbooks / Zarida Zaman."}, {"num": 1, "name": "The fashion design reference + specification book : everything fashion designers need to know every"}, {"num": 1, "name": "200 projects to get you into fashion design / Tracey Fitzgerald and Adrian Grandon."}, {"num": 1, "name": "The fashion designer's directory of shape and form / Simon Travers-Spencer, Zarida Zaman."}]}, {"num": 2, "name": "745", "children": [{"num": 1, "name": "One day / [Publiisher : Sylvie Estrada ; concept and art direction : Emil Kozak ; layout & design :"}, {"num": 1, "name": "Thinking design / S. Balaram."}]}, {"num": 1, "name": "741", "children": [{"num": 1, "name": "Making a splash : graphics that flow : graphic identities / print work / illustrations / typography"}]}]}, {"num": 3, "name": "79", "children": [{"num": 2, "name": "791", "children": [{"num": 1, "name": "Indie 2.0 : change and continuity in contemporary American indie film / Geoff King."}, {"num": 1, "name": "M & A : a practical guide to doing the deal / Jeffrey C. Hooke."}]}, {"num": 1, "name": "794", "children": [{"num": 1, "name": "Digital games : a context for cognitive development  / Fran C. Blumberg, Shalom M. Fisch, editors."}]}]}, {"num": 2, "name": "75", "children": [{"num": 2, "name": "759", "children": [{"num": 1, "name": "Utopia : the genius of Emily Kame Kngwarreye / edited by Margo Neale."}, {"num": 1, "name": "Remembering forward : Australian Aboriginal painting since 1960 / edited by Kasper Konig, Emily Joyc"}]}]}, {"num": 1, "name": "77", "children": [{"num": 1, "name": "777", "children": [{"num": 1, "name": "Master shots. Vol. 2 : 100 ways to shoot great dialogue scenes / Christopher Kenworthy."}]}]}]}, {"num": 3, "name": "8", "children": [{"num": 2, "name": "80", "children": [{"num": 2, "name": "808", "children": [{"num": 1, "name": "Writing television sitcoms / Evan S. Smith."}, {"num": 1, "name": "The basics of essay writing / Nigel Warburton."}]}]}, {"num": 1, "name": "82", "children": [{"num": 1, "name": "823", "children": [{"num": 1, "name": "The loved one : an Anglo-American tragedy / Evelyn Waugh"}]}]}]}, {"num": 3, "name": "0", "children": [{"num": 1, "name": "00", "children": [{"num": 1, "name": "001", "children": [{"num": 1, "name": "The craft of research / Wayne C. Booth, Gregory G. Colomb, Joseph M. Williams."}]}]}, {"num": 1, "name": "02", "children": [{"num": 1, "name": "026", "children": [{"num": 1, "name": "Postcards in the library : invaluable visual resources / Norman D. Stevens, editor."}]}]}, {"num": 1, "name": "06", "children": [{"num": 1, "name": "061", "children": [{"num": 1, "name": "The nature of the nonprofit sector / edited by J. Steven Ott, Lisa A. Dicke."}]}]}]}, {"num": 4, "name": "1", "children": [{"num": 2, "name": "15", "children": [{"num": 1, "name": "153", "children": [{"num": 1, "name": "Space and place : the perspective of experience / Yi-Fu Tuan."}]}, {"num": 1, "name": "155", "children": [{"num": 1, "name": "Princess cultures : mediating girls' imaginations and identities / edited by Miriam Forman-Brunell &"}]}]}, {"num": 1, "name": "17", "children": [{"num": 1, "name": "174", "children": [{"num": 1, "name": "Principles of biomedical ethics / Tom L. Beauchamp, James F. Childress."}]}]}, {"num": 1, "name": "12", "children": [{"num": 1, "name": "128", "children": [{"num": 1, "name": "Meaning, subjectivity, society : making sense of modernity / by Karl E. Smith."}]}]}]}, {"num": 2, "name": "9", "children": [{"num": 2, "name": "91", "children": [{"num": 2, "name": "910", "children": [{"num": 2, "name": "Geographic information systems and science / Paul A. Longley ... [et al.]."}]}]}]}]}